{"gap": {"type": "relative", "arguments": {"name": "GAP -296091488377847865", "modelCrop": "WC", "rate": 250.0, "apply_every_n_years": 1, "number_of_applications": 2, "interval": 14, "model_specific_data": {}, "bbch": 31, "season": 0}}, "compound": {"molarMass": 300.0, "water_solubility": 0.010384432927732098, "vapor_pressure": 3.896915117386684e-05, "reference_temperature": 20.0, "koc": 2110.2106379425354, "freundlich": 0.7976106615615868, "dt50": {"system": 6.0, "soil": 190.90092222307106, "surfaceWater": 6.0, "sediment": 6.0}, "plant_uptake": 0.0, "name": "Compound 8361680110628982497", "model_specific_data": {}, "metabolites": [{"formation_fraction": 0.2, "metabolite": {"molarMass": 300.0, "water_solubility": 0.00037970737492484634, "vapor_pressure": 8.195190103780406e-06, "reference_temperature": 20.0, "koc": 196.9857949462534, "freundlich": 1.0079069735516248, "dt50": {"system": 6.0, "soil": 228.82087783164366, "surfaceWater": 6.0, "sediment": 6.0}, "plant_uptake": 0.5, "name": "Compound 2626971116419643945", "model_specific_data": {}, "metabolites": []}}]}}