{"gap": {"type": "relative", "arguments": {"name": "GAP -296091488377847865", "modelCrop": "WC", "rate": 250.0, "apply_every_n_years": 1, "number_of_applications": 2, "interval": 14, "model_specific_data": {}, "bbch": 31, "season": 0}}, "compound": {"molarMass": 300.0, "water_solubility": 0.020106486829783166, "vapor_pressure": 0.0251682434018484, "reference_temperature": 20.0, "koc": 2051.5193619548954, "freundlich": 0.9550994796436757, "dt50": {"system": 6.0, "soil": 68.47444334905569, "surfaceWater": 6.0, "sediment": 6.0}, "plant_uptake": 0.0, "name": "Compound 16370233991035998", "model_specific_data": {}, "metabolites": [{"formation_fraction": 0.2, "metabolite": {"molarMass": 300.0, "water_solubility": 0.024183414201253122, "vapor_pressure": 5.528512336509685e-07, "reference_temperature": 20.0, "koc": 16.410115581602593, "freundlich": 0.9743800729271375, "dt50": {"system": 6.0, "soil": 73.40769211819826, "surfaceWater": 6.0, "sediment": 6.0}, "plant_uptake": 0.5, "name": "Compound -4974082227166773483", "model_specific_data": {}, "metabolites": []}}]}}