{"gap": {"type": "relative", "arguments": {"name": "GAP -296091488377847865", "modelCrop": "WC", "rate": 250.0, "apply_every_n_years": 1, "number_of_applications": 2, "interval": 14, "model_specific_data": {}, "bbch": 31, "season": 0}}, "compound": {"molarMass": 300.0, "water_solubility": 0.0014401462137418677, "vapor_pressure": 6.65659802913475e-05, "reference_temperature": 20.0, "koc": 29.30489693893823, "freundlich": 1.1226170531084407, "dt50": {"system": 6.0, "soil": 113.63752024914213, "surfaceWater": 6.0, "sediment": 6.0}, "plant_uptake": 0.0, "name": "Compound 3063757895059235435", "model_specific_data": {}, "metabolites": [{"formation_fraction": 0.2, "metabolite": {"molarMass": 300.0, "water_solubility": 0.11127329848125968, "vapor_pressure": 1.2743873994882886e-06, "reference_temperature": 20.0, "koc": 143.73607944539964, "freundlich": 1.1501421227404283, "dt50": {"system": 6.0, "soil": 291.8617915391678, "surfaceWater": 6.0, "sediment": 6.0}, "plant_uptake": 0.5, "name": "Compound 3722287654000851662", "model_specific_data": {}, "metabolites": []}}]}}