{"gap": {"type": "relative", "arguments": {"name": "GAP -296091488377847865", "modelCrop": "WC", "rate": 250.0, "apply_every_n_years": 1, "number_of_applications": 2, "interval": 14, "model_specific_data": {}, "bbch": 31, "season": 0}}, "compound": {"molarMass": 300.0, "water_solubility": 0.0010513762244526656, "vapor_pressure": 1.632778291583684e-07, "reference_temperature": 20.0, "koc": 553.7779658699657, "freundlich": 0.9719969046918362, "dt50": {"system": 6.0, "soil": 69.19035198912943, "surfaceWater": 6.0, "sediment": 6.0}, "plant_uptake": 0.0, "name": "Compound 1492159513264354004", "model_specific_data": {}, "metabolites": [{"formation_fraction": 0.2, "metabolite": {"molarMass": 300.0, "water_solubility": 0.00031457659607715015, "vapor_pressure": 8.274779760248605e-05, "reference_temperature": 20.0, "koc": 1417.9131446919541, "freundlich": 1.1601977714404228, "dt50": {"system": 6.0, "soil": 93.28542614922924, "surfaceWater": 6.0, "sediment": 6.0}, "plant_uptake": 0.5, "name": "Compound -8464746734056251112", "model_specific_data": {}, "metabolites": []}}]}}