{"gap": {"type": "relative", "arguments": {"name": "GAP -296091488377847865", "modelCrop": "WC", "rate": 250.0, "apply_every_n_years": 1, "number_of_applications": 2, "interval": 14, "model_specific_data": {}, "bbch": 31, "season": 0}}, "compound": {"molarMass": 300.0, "water_solubility": 0.029967231449757218, "vapor_pressure": 9.762306638216909e-08, "reference_temperature": 20.0, "koc": 76.72203014121924, "freundlich": 0.8313583134939433, "dt50": {"system": 6.0, "soil": 19.10603731288686, "surfaceWater": 6.0, "sediment": 6.0}, "plant_uptake": 0.0, "name": "Compound -627521803562436264", "model_specific_data": {}, "metabolites": [{"formation_fraction": 0.2, "metabolite": {"molarMass": 300.0, "water_solubility": 0.023579696980591272, "vapor_pressure": 1.1170975969078517e-07, "reference_temperature": 20.0, "koc": 44.49351224583488, "freundlich": 0.9433845158001708, "dt50": {"system": 6.0, "soil": 168.98206746403264, "surfaceWater": 6.0, "sediment": 6.0}, "plant_uptake": 0.5, "name": "Compound 1121948250192980958", "model_specific_data": {}, "metabolites": []}}]}}