{"gap": {"type": "relative", "arguments": {"name": "GAP -296091488377847865", "modelCrop": "WC", "rate": 250.0, "apply_every_n_years": 1, "number_of_applications": 2, "interval": 14, "model_specific_data": {}, "bbch": 31, "season": 0}}, "compound": {"molarMass": 300.0, "water_solubility": 0.36679561991432935, "vapor_pressure": 2.5178136865362813e-06, "reference_temperature": 20.0, "koc": 3478.1485897601897, "freundlich": 0.9366165442981428, "dt50": {"system": 6.0, "soil": 266.0269669261089, "surfaceWater": 6.0, "sediment": 6.0}, "plant_uptake": 0.0, "name": "Compound -4511092190095556784", "model_specific_data": {}, "metabolites": [{"formation_fraction": 0.2, "metabolite": {"molarMass": 300.0, "water_solubility": 0.15008861102635815, "vapor_pressure": 0.0006444516120242335, "reference_temperature": 20.0, "koc": 61.88011998781909, "freundlich": 1.0613948430110398, "dt50": {"system": 6.0, "soil": 245.85076344296735, "surfaceWater": 6.0, "sediment": 6.0}, "plant_uptake": 0.5, "name": "Compound 5354158860307006264", "model_specific_data": {}, "metabolites": []}}]}}