{"gap": {"type": "relative", "arguments": {"name": "GAP -296091488377847865", "modelCrop": "WC", "rate": 250.0, "apply_every_n_years": 1, "number_of_applications": 2, "interval": 14, "model_specific_data": {}, "bbch": 31, "season": 0}}, "compound": {"molarMass": 300.0, "water_solubility": 0.1787535184463783, "vapor_pressure": 6.514347618220562e-07, "reference_temperature": 20.0, "koc": 128.93230184290428, "freundlich": 1.150147817929533, "dt50": {"system": 6.0, "soil": 159.5641420841967, "surfaceWater": 6.0, "sediment": 6.0}, "plant_uptake": 0.0, "name": "Compound 1105708904341892695", "model_specific_data": {}, "metabolites": [{"formation_fraction": 0.2, "metabolite": {"molarMass": 300.0, "water_solubility": 0.0010779319532362925, "vapor_pressure": 1.963788577686391e-06, "reference_temperature": 20.0, "koc": 88.7097794568773, "freundlich": 1.0461512699682407, "dt50": {"system": 6.0, "soil": 9.909884174001967, "surfaceWater": 6.0, "sediment": 6.0}, "plant_uptake": 0.5, "name": "Compound -2335054450802834951", "model_specific_data": {}, "metabolites": []}}]}}