{"gap": {"type": "relative", "arguments": {"name": "GAP -296091488377847865", "modelCrop": "WC", "rate": 250.0, "apply_every_n_years": 1, "number_of_applications": 2, "interval": 14, "model_specific_data": {}, "bbch": 31, "season": 0}}, "compound": {"molarMass": 300.0, "water_solubility": 0.005275346268425593, "vapor_pressure": 1.1478426728469936e-06, "reference_temperature": 20.0, "koc": 715.4532488979077, "freundlich": 0.9055462788930668, "dt50": {"system": 6.0, "soil": 284.0347529703407, "surfaceWater": 6.0, "sediment": 6.0}, "plant_uptake": 0.0, "name": "Compound -6841924506406197282", "model_specific_data": {}, "metabolites": [{"formation_fraction": 0.2, "metabolite": {"molarMass": 300.0, "water_solubility": 0.004043768646803011, "vapor_pressure": 5.486929617869838e-05, "reference_temperature": 20.0, "koc": 58.64277591048113, "freundlich": 0.9619518437339483, "dt50": {"system": 6.0, "soil": 204.07200269627373, "surfaceWater": 6.0, "sediment": 6.0}, "plant_uptake": 0.5, "name": "Compound -8559122993654844874", "model_specific_data": {}, "metabolites": []}}]}}