{"gap": {"type": "relative", "arguments": {"name": "GAP -296091488377847865", "modelCrop": "WC", "rate": 250.0, "apply_every_n_years": 1, "number_of_applications": 2, "interval": 14, "model_specific_data": {}, "bbch": 31, "season": 0}}, "compound": {"molarMass": 300.0, "water_solubility": 0.002507440309589382, "vapor_pressure": 3.1707667235978824e-08, "reference_temperature": 20.0, "koc": 523.9023454773087, "freundlich": 0.7446623938708483, "dt50": {"system": 6.0, "soil": 98.45754809494838, "surfaceWater": 6.0, "sediment": 6.0}, "plant_uptake": 0.0, "name": "Compound -748340745640218083", "model_specific_data": {}, "metabolites": [{"formation_fraction": 0.2, "metabolite": {"molarMass": 300.0, "water_solubility": 0.0037764547610634187, "vapor_pressure": 1.4487772336872248e-07, "reference_temperature": 20.0, "koc": 3050.957883350385, "freundlich": 0.9192258827512025, "dt50": {"system": 6.0, "soil": 227.66825002667403, "surfaceWater": 6.0, "sediment": 6.0}, "plant_uptake": 0.5, "name": "Compound 6262244914641350685", "model_specific_data": {}, "metabolites": []}}]}}