{"gap": {"type": "relative", "arguments": {"name": "GAP -296091488377847865", "modelCrop": "WC", "rate": 250.0, "apply_every_n_years": 1, "number_of_applications": 2, "interval": 14, "model_specific_data": {}, "bbch": 31, "season": 0}}, "compound": {"molarMass": 300.0, "water_solubility": 0.016448759422538616, "vapor_pressure": 4.2937411704894073e-08, "reference_temperature": 20.0, "koc": 3082.1221025962145, "freundlich": 1.0208018769656542, "dt50": {"system": 6.0, "soil": 160.8577010438557, "surfaceWater": 6.0, "sediment": 6.0}, "plant_uptake": 0.0, "name": "Compound 7812703435768823282", "model_specific_data": {}, "metabolites": [{"formation_fraction": 0.2, "metabolite": {"molarMass": 300.0, "water_solubility": 0.0008031663252510652, "vapor_pressure": 2.6585273168260873e-05, "reference_temperature": 20.0, "koc": 350.599519175492, "freundlich": 0.9555771931384108, "dt50": {"system": 6.0, "soil": 53.755504281312504, "surfaceWater": 6.0, "sediment": 6.0}, "plant_uptake": 0.5, "name": "Compound -7290572252484829048", "model_specific_data": {}, "metabolites": []}}]}}