{"gap": {"type": "relative", "arguments": {"name": "GAP -296091488377847865", "modelCrop": "WC", "rate": 250.0, "apply_every_n_years": 1, "number_of_applications": 2, "interval": 14, "model_specific_data": {}, "bbch": 31, "season": 0}}, "compound": {"molarMass": 300.0, "water_solubility": 0.060847243600313725, "vapor_pressure": 0.00039496999622000656, "reference_temperature": 20.0, "koc": 4500.177102056413, "freundlich": 0.8863263521022984, "dt50": {"system": 6.0, "soil": 141.17733573555537, "surfaceWater": 6.0, "sediment": 6.0}, "plant_uptake": 0.0, "name": "Compound 2461192419877371632", "model_specific_data": {}, "metabolites": [{"formation_fraction": 0.2, "metabolite": {"molarMass": 300.0, "water_solubility": 0.11058962516145475, "vapor_pressure": 0.0003254824608915178, "reference_temperature": 20.0, "koc": 79.20706428822038, "freundlich": 0.8820062979733292, "dt50": {"system": 6.0, "soil": 219.64285047099378, "surfaceWater": 6.0, "sediment": 6.0}, "plant_uptake": 0.5, "name": "Compound 3872020819633315702", "model_specific_data": {}, "metabolites": []}}]}}