{"gap": {"type": "relative", "arguments": {"name": "GAP -296091488377847865", "modelCrop": "WC", "rate": 250.0, "apply_every_n_years": 1, "number_of_applications": 2, "interval": 14, "model_specific_data": {}, "bbch": 31, "season": 0}}, "compound": {"molarMass": 300.0, "water_solubility": 4.8199459589280794e-05, "vapor_pressure": 1.3703882020741164e-05, "reference_temperature": 20.0, "koc": 297.031306892362, "freundlich": 1.066534023605958, "dt50": {"system": 6.0, "soil": 105.59678365942507, "surfaceWater": 6.0, "sediment": 6.0}, "plant_uptake": 0.0, "name": "Compound 2534973136464193231", "model_specific_data": {}, "metabolites": [{"formation_fraction": 0.2, "metabolite": {"molarMass": 300.0, "water_solubility": 0.046634213637475025, "vapor_pressure": 6.206022627193469e-06, "reference_temperature": 20.0, "koc": 74.77501015382356, "freundlich": 0.9055227454399594, "dt50": {"system": 6.0, "soil": 121.99854683932068, "surfaceWater": 6.0, "sediment": 6.0}, "plant_uptake": 0.5, "name": "Compound -2751935564193223014", "model_specific_data": {}, "metabolites": []}}]}}