{"gap": {"type": "relative", "arguments": {"name": "GAP -296091488377847865", "modelCrop": "WC", "rate": 250.0, "apply_every_n_years": 1, "number_of_applications": 2, "interval": 14, "model_specific_data": {}, "bbch": 31, "season": 0}}, "compound": {"molarMass": 300.0, "water_solubility": 0.0004729154358253823, "vapor_pressure": 8.743018758453535e-06, "reference_temperature": 20.0, "koc": 31.9922860042176, "freundlich": 1.0573174041955125, "dt50": {"system": 6.0, "soil": 81.82456054819589, "surfaceWater": 6.0, "sediment": 6.0}, "plant_uptake": 0.0, "name": "Compound -9164010003804819130", "model_specific_data": {}, "metabolites": [{"formation_fraction": 0.2, "metabolite": {"molarMass": 300.0, "water_solubility": 0.025440778458681475, "vapor_pressure": 8.146276024722992e-08, "reference_temperature": 20.0, "koc": 2056.1936984087847, "freundlich": 0.9432919813853035, "dt50": {"system": 6.0, "soil": 196.39379929177903, "surfaceWater": 6.0, "sediment": 6.0}, "plant_uptake": 0.5, "name": "Compound -1435941179171172930", "model_specific_data": {}, "metabolites": []}}]}}