{"gap": {"type": "relative", "arguments": {"name": "GAP -296091488377847865", "modelCrop": "WC", "rate": 250.0, "apply_every_n_years": 1, "number_of_applications": 2, "interval": 14, "model_specific_data": {}, "bbch": 31, "season": 0}}, "compound": {"molarMass": 300.0, "water_solubility": 0.0005201467175881024, "vapor_pressure": 0.005126168497716471, "reference_temperature": 20.0, "koc": 254.16290366755487, "freundlich": 0.7035614564427215, "dt50": {"system": 6.0, "soil": 277.1968896946159, "surfaceWater": 6.0, "sediment": 6.0}, "plant_uptake": 0.0, "name": "Compound 4471776090162251290", "model_specific_data": {}, "metabolites": [{"formation_fraction": 0.2, "metabolite": {"molarMass": 300.0, "water_solubility": 0.01996807120709783, "vapor_pressure": 1.4539156889654267e-05, "reference_temperature": 20.0, "koc": 390.2647854831186, "freundlich": 0.980040915639421, "dt50": {"system": 6.0, "soil": 211.51991181881897, "surfaceWater": 6.0, "sediment": 6.0}, "plant_uptake": 0.5, "name": "Compound -317796349174966030", "model_specific_data": {}, "metabolites": []}}]}}