{"gap": {"type": "relative", "arguments": {"name": "GAP -296091488377847865", "modelCrop": "WC", "rate": 250.0, "apply_every_n_years": 1, "number_of_applications": 2, "interval": 14, "model_specific_data": {}, "bbch": 31, "season": 0}}, "compound": {"molarMass": 300.0, "water_solubility": 0.000395057453032091, "vapor_pressure": 5.04466988077741e-05, "reference_temperature": 20.0, "koc": 1301.1715839299159, "freundlich": 0.7506978763498666, "dt50": {"system": 6.0, "soil": 144.09681823261334, "surfaceWater": 6.0, "sediment": 6.0}, "plant_uptake": 0.0, "name": "Compound 4288097675858932846", "model_specific_data": {}, "metabolites": [{"formation_fraction": 0.2, "metabolite": {"molarMass": 300.0, "water_solubility": 0.0007266565093213274, "vapor_pressure": 2.1603811137526376e-08, "reference_temperature": 20.0, "koc": 19.781055286605305, "freundlich": 1.0375090823448745, "dt50": {"system": 6.0, "soil": 41.61771121997898, "surfaceWater": 6.0, "sediment": 6.0}, "plant_uptake": 0.5, "name": "Compound 2041161087099735795", "model_specific_data": {}, "metabolites": []}}]}}