{"gap": {"type": "relative", "arguments": {"name": "GAP -296091488377847865", "modelCrop": "WC", "rate": 250.0, "apply_every_n_years": 1, "number_of_applications": 2, "interval": 14, "model_specific_data": {}, "bbch": 31, "season": 0}}, "compound": {"molarMass": 300.0, "water_solubility": 0.18855419310898955, "vapor_pressure": 0.0006881707039417139, "reference_temperature": 20.0, "koc": 788.5643823464756, "freundlich": 0.9478365173479089, "dt50": {"system": 6.0, "soil": 56.17662892749624, "surfaceWater": 6.0, "sediment": 6.0}, "plant_uptake": 0.0, "name": "Compound 4777186034214816959", "model_specific_data": {}, "metabolites": [{"formation_fraction": 0.2, "metabolite": {"molarMass": 300.0, "water_solubility": 0.03248439548357326, "vapor_pressure": 0.0008344176763720031, "reference_temperature": 20.0, "koc": 2981.6717745064816, "freundlich": 1.19177839551641, "dt50": {"system": 6.0, "soil": 80.87307398654099, "surfaceWater": 6.0, "sediment": 6.0}, "plant_uptake": 0.5, "name": "Compound 6264997181907153862", "model_specific_data": {}, "metabolites": []}}]}}