{"gap": {"type": "relative", "arguments": {"name": "GAP -296091488377847865", "modelCrop": "WC", "rate": 250.0, "apply_every_n_years": 1, "number_of_applications": 2, "interval": 14, "model_specific_data": {}, "bbch": 31, "season": 0}}, "compound": {"molarMass": 300.0, "water_solubility": 0.24122034886295513, "vapor_pressure": 8.68671140823827e-06, "reference_temperature": 20.0, "koc": 27.479071718480718, "freundlich": 0.7283978239256923, "dt50": {"system": 6.0, "soil": 180.28107591846168, "surfaceWater": 6.0, "sediment": 6.0}, "plant_uptake": 0.0, "name": "Compound 6805002380429701328", "model_specific_data": {}, "metabolites": [{"formation_fraction": 0.2, "metabolite": {"molarMass": 300.0, "water_solubility": 0.01916193213088723, "vapor_pressure": 1.4293804382255899e-06, "reference_temperature": 20.0, "koc": 239.6288963531892, "freundlich": 0.7243204239482106, "dt50": {"system": 6.0, "soil": 89.90126137515438, "surfaceWater": 6.0, "sediment": 6.0}, "plant_uptake": 0.5, "name": "Compound -1052702188122302690", "model_specific_data": {}, "metabolites": []}}]}}