{"gap": {"type": "relative", "arguments": {"name": "GAP -296091488377847865", "modelCrop": "WC", "rate": 250.0, "apply_every_n_years": 1, "number_of_applications": 2, "interval": 14, "model_specific_data": {}, "bbch": 31, "season": 0}}, "compound": {"molarMass": 300.0, "water_solubility": 0.005698481715627117, "vapor_pressure": 1.1191178748623676e-07, "reference_temperature": 20.0, "koc": 3934.2440491161956, "freundlich": 1.1929246527507849, "dt50": {"system": 6.0, "soil": 41.45681151450227, "surfaceWater": 6.0, "sediment": 6.0}, "plant_uptake": 0.0, "name": "Compound -6661724352938838349", "model_specific_data": {}, "metabolites": [{"formation_fraction": 0.2, "metabolite": {"molarMass": 300.0, "water_solubility": 0.01051199844054284, "vapor_pressure": 3.781911646199922e-06, "reference_temperature": 20.0, "koc": 60.25379516387822, "freundlich": 1.1327786386522034, "dt50": {"system": 6.0, "soil": 129.57460637686967, "surfaceWater": 6.0, "sediment": 6.0}, "plant_uptake": 0.5, "name": "Compound -7238693900210884426", "model_specific_data": {}, "metabolites": []}}]}}