{"gap": {"type": "relative", "arguments": {"name": "GAP -296091488377847865", "modelCrop": "WC", "rate": 250.0, "apply_every_n_years": 1, "number_of_applications": 2, "interval": 14, "model_specific_data": {}, "bbch": 31, "season": 0}}, "compound": {"molarMass": 300.0, "water_solubility": 0.0002234462578503013, "vapor_pressure": 1.8713831769535835e-06, "reference_temperature": 20.0, "koc": 112.0899895713517, "freundlich": 1.1974174885110556, "dt50": {"system": 6.0, "soil": 201.84993655223772, "surfaceWater": 6.0, "sediment": 6.0}, "plant_uptake": 0.0, "name": "Compound 4596451414873219271", "model_specific_data": {}, "metabolites": [{"formation_fraction": 0.2, "metabolite": {"molarMass": 300.0, "water_solubility": 0.044851502839774446, "vapor_pressure": 8.014719483263363e-09, "reference_temperature": 20.0, "koc": 85.30369148345018, "freundlich": 0.893978001241701, "dt50": {"system": 6.0, "soil": 201.77770909163354, "surfaceWater": 6.0, "sediment": 6.0}, "plant_uptake": 0.5, "name": "Compound -3952007745474426270", "model_specific_data": {}, "metabolites": []}}]}}