{"gap": {"type": "relative", "arguments": {"name": "GAP -296091488377847865", "modelCrop": "WC", "rate": 250.0, "apply_every_n_years": 1, "number_of_applications": 2, "interval": 14, "model_specific_data": {}, "bbch": 31, "season": 0}}, "compound": {"molarMass": 300.0, "water_solubility": 0.00046122725344517314, "vapor_pressure": 5.701310345286506e-07, "reference_temperature": 20.0, "koc": 2351.227325345914, "freundlich": 1.0375106416676316, "dt50": {"system": 6.0, "soil": 117.05422034218901, "surfaceWater": 6.0, "sediment": 6.0}, "plant_uptake": 0.0, "name": "Compound -1179043528178911053", "model_specific_data": {}, "metabolites": [{"formation_fraction": 0.2, "metabolite": {"molarMass": 300.0, "water_solubility": 0.007699933147841471, "vapor_pressure": 2.7400434278972757e-06, "reference_temperature": 20.0, "koc": 38.548550938244304, "freundlich": 0.8536081579686727, "dt50": {"system": 6.0, "soil": 273.89349864528265, "surfaceWater": 6.0, "sediment": 6.0}, "plant_uptake": 0.5, "name": "Compound -2399371308057947400", "model_specific_data": {}, "metabolites": []}}]}}