{"gap": {"type": "relative", "arguments": {"name": "GAP -296091488377847865", "modelCrop": "WC", "rate": 250.0, "apply_every_n_years": 1, "number_of_applications": 2, "interval": 14, "model_specific_data": {}, "bbch": 31, "season": 0}}, "compound": {"molarMass": 300.0, "water_solubility": 0.007208881189142007, "vapor_pressure": 0.0002628778427248022, "reference_temperature": 20.0, "koc": 1058.1182539097638, "freundlich": 1.0881735645078192, "dt50": {"system": 6.0, "soil": 264.4182780915837, "surfaceWater": 6.0, "sediment": 6.0}, "plant_uptake": 0.0, "name": "Compound 2574867084629261513", "model_specific_data": {}, "metabolites": [{"formation_fraction": 0.2, "metabolite": {"molarMass": 300.0, "water_solubility": 0.0005929453417321202, "vapor_pressure": 2.3739697397263864e-05, "reference_temperature": 20.0, "koc": 46.214873367620164, "freundlich": 0.88605792516665, "dt50": {"system": 6.0, "soil": 266.33450560263196, "surfaceWater": 6.0, "sediment": 6.0}, "plant_uptake": 0.5, "name": "Compound -2147685061320487086", "model_specific_data": {}, "metabolites": []}}]}}