{"gap": {"type": "relative", "arguments": {"name": "GAP -296091488377847865", "modelCrop": "WC", "rate": 250.0, "apply_every_n_years": 1, "number_of_applications": 2, "interval": 14, "model_specific_data": {}, "bbch": 31, "season": 0}}, "compound": {"molarMass": 300.0, "water_solubility": 0.009655021795867096, "vapor_pressure": 2.009965129505494e-06, "reference_temperature": 20.0, "koc": 57.95777739193587, "freundlich": 0.9053124973077873, "dt50": {"system": 6.0, "soil": 51.38671397466198, "surfaceWater": 6.0, "sediment": 6.0}, "plant_uptake": 0.0, "name": "Compound -157506284170273453", "model_specific_data": {}, "metabolites": [{"formation_fraction": 0.2, "metabolite": {"molarMass": 300.0, "water_solubility": 0.004186495868458431, "vapor_pressure": 0.0017872089957561938, "reference_temperature": 20.0, "koc": 83.6063819205881, "freundlich": 1.0527103723079447, "dt50": {"system": 6.0, "soil": 23.20062298093356, "surfaceWater": 6.0, "sediment": 6.0}, "plant_uptake": 0.5, "name": "Compound 7955344368861919118", "model_specific_data": {}, "metabolites": []}}]}}