{"gap": {"type": "relative", "arguments": {"name": "GAP -296091488377847865", "modelCrop": "WC", "rate": 250.0, "apply_every_n_years": 1, "number_of_applications": 2, "interval": 14, "model_specific_data": {}, "bbch": 31, "season": 0}}, "compound": {"molarMass": 300.0, "water_solubility": 0.0093790474759921, "vapor_pressure": 0.0001927862539836574, "reference_temperature": 20.0, "koc": 418.8512246153837, "freundlich": 1.1495256574354273, "dt50": {"system": 6.0, "soil": 173.3134018633408, "surfaceWater": 6.0, "sediment": 6.0}, "plant_uptake": 0.0, "name": "Compound 6229113199191892326", "model_specific_data": {}, "metabolites": [{"formation_fraction": 0.2, "metabolite": {"molarMass": 300.0, "water_solubility": 0.015589755678598384, "vapor_pressure": 4.000278462507045e-07, "reference_temperature": 20.0, "koc": 204.2037788856863, "freundlich": 1.0540468591277756, "dt50": {"system": 6.0, "soil": 9.876813872799598, "surfaceWater": 6.0, "sediment": 6.0}, "plant_uptake": 0.5, "name": "Compound -1167716053410433364", "model_specific_data": {}, "metabolites": []}}]}}