{"gap": {"type": "relative", "arguments": {"name": "GAP -296091488377847865", "modelCrop": "WC", "rate": 250.0, "apply_every_n_years": 1, "number_of_applications": 2, "interval": 14, "model_specific_data": {}, "bbch": 31, "season": 0}}, "compound": {"molarMass": 300.0, "water_solubility": 0.0023408782193158686, "vapor_pressure": 5.49161603145574e-06, "reference_temperature": 20.0, "koc": 68.41634621578258, "freundlich": 1.1533501746057926, "dt50": {"system": 6.0, "soil": 238.7522054478731, "surfaceWater": 6.0, "sediment": 6.0}, "plant_uptake": 0.0, "name": "Compound -3107466761506466213", "model_specific_data": {}, "metabolites": [{"formation_fraction": 0.2, "metabolite": {"molarMass": 300.0, "water_solubility": 0.20825904597858985, "vapor_pressure": 7.230015465208189e-06, "reference_temperature": 20.0, "koc": 519.0119659997522, "freundlich": 1.1656474167696242, "dt50": {"system": 6.0, "soil": 202.60351947098658, "surfaceWater": 6.0, "sediment": 6.0}, "plant_uptake": 0.5, "name": "Compound -5916151592216851582", "model_specific_data": {}, "metabolites": []}}]}}