{"gap": {"type": "relative", "arguments": {"name": "GAP -296091488377847865", "modelCrop": "WC", "rate": 250.0, "apply_every_n_years": 1, "number_of_applications": 2, "interval": 14, "model_specific_data": {}, "bbch": 31, "season": 0}}, "compound": {"molarMass": 300.0, "water_solubility": 0.0004707198047001167, "vapor_pressure": 2.8441689159121094e-05, "reference_temperature": 20.0, "koc": 1140.1365604249534, "freundlich": 0.9095562599031894, "dt50": {"system": 6.0, "soil": 164.48798980140225, "surfaceWater": 6.0, "sediment": 6.0}, "plant_uptake": 0.0, "name": "Compound 1927270818562929861", "model_specific_data": {}, "metabolites": [{"formation_fraction": 0.2, "metabolite": {"molarMass": 300.0, "water_solubility": 0.003940017366074648, "vapor_pressure": 1.6693568637764801e-06, "reference_temperature": 20.0, "koc": 182.0755966355797, "freundlich": 0.8509500711464334, "dt50": {"system": 6.0, "soil": 142.0334825166854, "surfaceWater": 6.0, "sediment": 6.0}, "plant_uptake": 0.5, "name": "Compound 6352508310868582586", "model_specific_data": {}, "metabolites": []}}]}}