{"gap": {"type": "relative", "arguments": {"name": "GAP -296091488377847865", "modelCrop": "WC", "rate": 250.0, "apply_every_n_years": 1, "number_of_applications": 2, "interval": 14, "model_specific_data": {}, "bbch": 31, "season": 0}}, "compound": {"molarMass": 300.0, "water_solubility": 0.001401550017817161, "vapor_pressure": 1.178645382685632e-06, "reference_temperature": 20.0, "koc": 3920.4702292214356, "freundlich": 1.1482111778996886, "dt50": {"system": 6.0, "soil": 73.64384589199368, "surfaceWater": 6.0, "sediment": 6.0}, "plant_uptake": 0.0, "name": "Compound -326066226088314560", "model_specific_data": {}, "metabolites": [{"formation_fraction": 0.2, "metabolite": {"molarMass": 300.0, "water_solubility": 0.24928459619590637, "vapor_pressure": 3.822262743284292e-07, "reference_temperature": 20.0, "koc": 234.50407940872475, "freundlich": 1.1698020871164683, "dt50": {"system": 6.0, "soil": 186.31319932115414, "surfaceWater": 6.0, "sediment": 6.0}, "plant_uptake": 0.5, "name": "Compound -4258165426159092140", "model_specific_data": {}, "metabolites": []}}]}}