{"gap": {"type": "relative", "arguments": {"name": "GAP -296091488377847865", "modelCrop": "WC", "rate": 250.0, "apply_every_n_years": 1, "number_of_applications": 2, "interval": 14, "model_specific_data": {}, "bbch": 31, "season": 0}}, "compound": {"molarMass": 300.0, "water_solubility": 0.009025344771232837, "vapor_pressure": 8.627723897953424e-07, "reference_temperature": 20.0, "koc": 19.479739135181575, "freundlich": 0.8743254033663872, "dt50": {"system": 6.0, "soil": 297.6061939273533, "surfaceWater": 6.0, "sediment": 6.0}, "plant_uptake": 0.0, "name": "Compound -2025337978296513541", "model_specific_data": {}, "metabolites": [{"formation_fraction": 0.2, "metabolite": {"molarMass": 300.0, "water_solubility": 0.6525698608442526, "vapor_pressure": 7.403418921764954e-07, "reference_temperature": 20.0, "koc": 28.739367557547514, "freundlich": 1.0961322775001572, "dt50": {"system": 6.0, "soil": 168.68910976895867, "surfaceWater": 6.0, "sediment": 6.0}, "plant_uptake": 0.5, "name": "Compound -8744141829394652371", "model_specific_data": {}, "metabolites": []}}]}}