{"gap": {"type": "relative", "arguments": {"name": "GAP -296091488377847865", "modelCrop": "WC", "rate": 250.0, "apply_every_n_years": 1, "number_of_applications": 2, "interval": 14, "model_specific_data": {}, "bbch": 31, "season": 0}}, "compound": {"molarMass": 300.0, "water_solubility": 0.011409995096967633, "vapor_pressure": 4.2462306591963935e-05, "reference_temperature": 20.0, "koc": 174.5115412956884, "freundlich": 0.8438272327194825, "dt50": {"system": 6.0, "soil": 223.9661624266951, "surfaceWater": 6.0, "sediment": 6.0}, "plant_uptake": 0.0, "name": "Compound -1772472343184971792", "model_specific_data": {}, "metabolites": [{"formation_fraction": 0.2, "metabolite": {"molarMass": 300.0, "water_solubility": 0.00016616779624904648, "vapor_pressure": 2.675118486368508e-06, "reference_temperature": 20.0, "koc": 2062.6803989307864, "freundlich": 0.7382820815036883, "dt50": {"system": 6.0, "soil": 66.87184498851423, "surfaceWater": 6.0, "sediment": 6.0}, "plant_uptake": 0.5, "name": "Compound 2230334313802092309", "model_specific_data": {}, "metabolites": []}}]}}