{"gap": {"type": "relative", "arguments": {"name": "GAP -296091488377847865", "modelCrop": "WC", "rate": 250.0, "apply_every_n_years": 1, "number_of_applications": 2, "interval": 14, "model_specific_data": {}, "bbch": 31, "season": 0}}, "compound": {"molarMass": 300.0, "water_solubility": 0.0004420470984909256, "vapor_pressure": 1.4969704317264659e-06, "reference_temperature": 20.0, "koc": 173.15775292537728, "freundlich": 1.1210050628405888, "dt50": {"system": 6.0, "soil": 15.034086984784468, "surfaceWater": 6.0, "sediment": 6.0}, "plant_uptake": 0.0, "name": "Compound -4455661407012694760", "model_specific_data": {}, "metabolites": [{"formation_fraction": 0.2, "metabolite": {"molarMass": 300.0, "water_solubility": 0.0030145196043125182, "vapor_pressure": 0.0005228303021618497, "reference_temperature": 20.0, "koc": 188.61210986506813, "freundlich": 1.0072863578183195, "dt50": {"system": 6.0, "soil": 264.9353932162683, "surfaceWater": 6.0, "sediment": 6.0}, "plant_uptake": 0.5, "name": "Compound -3671758091535391249", "model_specific_data": {}, "metabolites": []}}]}}