{"gap": {"type": "relative", "arguments": {"name": "GAP -296091488377847865", "modelCrop": "WC", "rate": 250.0, "apply_every_n_years": 1, "number_of_applications": 2, "interval": 14, "model_specific_data": {}, "bbch": 31, "season": 0}}, "compound": {"molarMass": 300.0, "water_solubility": 0.005832608077183257, "vapor_pressure": 2.9061957619704456e-05, "reference_temperature": 20.0, "koc": 74.87087959085615, "freundlich": 0.985133462031934, "dt50": {"system": 6.0, "soil": 88.6569042635745, "surfaceWater": 6.0, "sediment": 6.0}, "plant_uptake": 0.0, "name": "Compound -4792679554515830512", "model_specific_data": {}, "metabolites": [{"formation_fraction": 0.2, "metabolite": {"molarMass": 300.0, "water_solubility": 0.02971310194008403, "vapor_pressure": 1.1907288439916083e-05, "reference_temperature": 20.0, "koc": 25.07073988691577, "freundlich": 0.7499483629911516, "dt50": {"system": 6.0, "soil": 297.6732153523698, "surfaceWater": 6.0, "sediment": 6.0}, "plant_uptake": 0.5, "name": "Compound -7167488567381430382", "model_specific_data": {}, "metabolites": []}}]}}