{"gap": {"type": "relative", "arguments": {"name": "GAP -296091488377847865", "modelCrop": "WC", "rate": 250.0, "apply_every_n_years": 1, "number_of_applications": 2, "interval": 14, "model_specific_data": {}, "bbch": 31, "season": 0}}, "compound": {"molarMass": 300.0, "water_solubility": 0.006744284197232365, "vapor_pressure": 3.10823447048426e-06, "reference_temperature": 20.0, "koc": 371.5931845533503, "freundlich": 0.8805508643010757, "dt50": {"system": 6.0, "soil": 295.27785494994373, "surfaceWater": 6.0, "sediment": 6.0}, "plant_uptake": 0.0, "name": "Compound 4205216746966326631", "model_specific_data": {}, "metabolites": [{"formation_fraction": 0.2, "metabolite": {"molarMass": 300.0, "water_solubility": 0.03187446159213021, "vapor_pressure": 1.218043432286882e-09, "reference_temperature": 20.0, "koc": 2492.2756060458064, "freundlich": 0.9102745186180361, "dt50": {"system": 6.0, "soil": 44.044597426033725, "surfaceWater": 6.0, "sediment": 6.0}, "plant_uptake": 0.5, "name": "Compound -17704405992757652", "model_specific_data": {}, "metabolites": []}}]}}