{"gap": {"type": "relative", "arguments": {"name": "GAP -296091488377847865", "modelCrop": "WC", "rate": 250.0, "apply_every_n_years": 1, "number_of_applications": 2, "interval": 14, "model_specific_data": {}, "bbch": 31, "season": 0}}, "compound": {"molarMass": 300.0, "water_solubility": 1.7764160726589788, "vapor_pressure": 1.6926891152508246e-05, "reference_temperature": 20.0, "koc": 330.4963544266466, "freundlich": 0.7118198301714943, "dt50": {"system": 6.0, "soil": 61.43714272959098, "surfaceWater": 6.0, "sediment": 6.0}, "plant_uptake": 0.0, "name": "Compound 7043191761651797593", "model_specific_data": {}, "metabolites": [{"formation_fraction": 0.2, "metabolite": {"molarMass": 300.0, "water_solubility": 0.012103591985328661, "vapor_pressure": 3.3779932270667373e-08, "reference_temperature": 20.0, "koc": 44.2328632023306, "freundlich": 1.029477238047509, "dt50": {"system": 6.0, "soil": 89.57542399238825, "surfaceWater": 6.0, "sediment": 6.0}, "plant_uptake": 0.5, "name": "Compound -3654745055624175795", "model_specific_data": {}, "metabolites": []}}]}}