{"gap": {"type": "relative", "arguments": {"name": "GAP -296091488377847865", "modelCrop": "WC", "rate": 250.0, "apply_every_n_years": 1, "number_of_applications": 2, "interval": 14, "model_specific_data": {}, "bbch": 31, "season": 0}}, "compound": {"molarMass": 300.0, "water_solubility": 0.1879215752078299, "vapor_pressure": 1.444236482919354e-07, "reference_temperature": 20.0, "koc": 12.501323837053002, "freundlich": 0.7695950564150633, "dt50": {"system": 6.0, "soil": 117.77306939799743, "surfaceWater": 6.0, "sediment": 6.0}, "plant_uptake": 0.0, "name": "Compound 18977685558052629", "model_specific_data": {}, "metabolites": [{"formation_fraction": 0.2, "metabolite": {"molarMass": 300.0, "water_solubility": 0.017544449373319424, "vapor_pressure": 0.00027806263269173465, "reference_temperature": 20.0, "koc": 4477.645771428668, "freundlich": 0.8513379575018358, "dt50": {"system": 6.0, "soil": 96.16898230908885, "surfaceWater": 6.0, "sediment": 6.0}, "plant_uptake": 0.5, "name": "Compound -3622222221142143341", "model_specific_data": {}, "metabolites": []}}]}}