{"gap": {"type": "relative", "arguments": {"name": "GAP -296091488377847865", "modelCrop": "WC", "rate": 250.0, "apply_every_n_years": 1, "number_of_applications": 2, "interval": 14, "model_specific_data": {}, "bbch": 31, "season": 0}}, "compound": {"molarMass": 300.0, "water_solubility": 0.45943879031936574, "vapor_pressure": 7.531430119990752e-06, "reference_temperature": 20.0, "koc": 3033.303485592923, "freundlich": 0.7798516741114849, "dt50": {"system": 6.0, "soil": 148.06110838942953, "surfaceWater": 6.0, "sediment": 6.0}, "plant_uptake": 0.0, "name": "Compound -1798395312248157529", "model_specific_data": {}, "metabolites": [{"formation_fraction": 0.2, "metabolite": {"molarMass": 300.0, "water_solubility": 0.02387880625218853, "vapor_pressure": 2.1982654150227545e-06, "reference_temperature": 20.0, "koc": 4851.374528062276, "freundlich": 1.164235551580431, "dt50": {"system": 6.0, "soil": 97.03982572669572, "surfaceWater": 6.0, "sediment": 6.0}, "plant_uptake": 0.5, "name": "Compound -4705892427106736014", "model_specific_data": {}, "metabolites": []}}]}}