{"gap": {"type": "relative", "arguments": {"name": "GAP -296091488377847865", "modelCrop": "WC", "rate": 250.0, "apply_every_n_years": 1, "number_of_applications": 2, "interval": 14, "model_specific_data": {}, "bbch": 31, "season": 0}}, "compound": {"molarMass": 300.0, "water_solubility": 0.007312326370971895, "vapor_pressure": 9.970893012537144e-06, "reference_temperature": 20.0, "koc": 532.7086199071477, "freundlich": 1.1618176487301255, "dt50": {"system": 6.0, "soil": 194.1672539718967, "surfaceWater": 6.0, "sediment": 6.0}, "plant_uptake": 0.0, "name": "Compound 1788525983464166489", "model_specific_data": {}, "metabolites": [{"formation_fraction": 0.2, "metabolite": {"molarMass": 300.0, "water_solubility": 0.0010949433561904744, "vapor_pressure": 2.19133051220862e-06, "reference_temperature": 20.0, "koc": 1238.1201359778074, "freundlich": 0.7733648939533089, "dt50": {"system": 6.0, "soil": 238.51652758217583, "surfaceWater": 6.0, "sediment": 6.0}, "plant_uptake": 0.5, "name": "Compound 6422545733469502094", "model_specific_data": {}, "metabolites": []}}]}}