{"gap": {"type": "relative", "arguments": {"name": "GAP -296091488377847865", "modelCrop": "WC", "rate": 250.0, "apply_every_n_years": 1, "number_of_applications": 2, "interval": 14, "model_specific_data": {}, "bbch": 31, "season": 0}}, "compound": {"molarMass": 300.0, "water_solubility": 0.15648774119121375, "vapor_pressure": 4.531763240842243e-09, "reference_temperature": 20.0, "koc": 158.99762758626582, "freundlich": 0.9902592943164719, "dt50": {"system": 6.0, "soil": 175.9402399569058, "surfaceWater": 6.0, "sediment": 6.0}, "plant_uptake": 0.0, "name": "Compound -2076904262754557778", "model_specific_data": {}, "metabolites": [{"formation_fraction": 0.2, "metabolite": {"molarMass": 300.0, "water_solubility": 0.002373379627592597, "vapor_pressure": 0.00015897886004322443, "reference_temperature": 20.0, "koc": 3684.7626159829224, "freundlich": 0.9700036972049407, "dt50": {"system": 6.0, "soil": 295.8840688272053, "surfaceWater": 6.0, "sediment": 6.0}, "plant_uptake": 0.5, "name": "Compound -7587966500722672053", "model_specific_data": {}, "metabolites": []}}]}}