{"gap": {"type": "relative", "arguments": {"name": "GAP -296091488377847865", "modelCrop": "WC", "rate": 250.0, "apply_every_n_years": 1, "number_of_applications": 2, "interval": 14, "model_specific_data": {}, "bbch": 31, "season": 0}}, "compound": {"molarMass": 300.0, "water_solubility": 0.02443833975680816, "vapor_pressure": 0.00033580132087063523, "reference_temperature": 20.0, "koc": 149.4565853578905, "freundlich": 0.8548750467973661, "dt50": {"system": 6.0, "soil": 96.50479062556802, "surfaceWater": 6.0, "sediment": 6.0}, "plant_uptake": 0.0, "name": "Compound -3466616852498973948", "model_specific_data": {}, "metabolites": [{"formation_fraction": 0.2, "metabolite": {"molarMass": 300.0, "water_solubility": 0.003866558620948905, "vapor_pressure": 2.257258816645549e-06, "reference_temperature": 20.0, "koc": 440.69340060491146, "freundlich": 1.0621629872781588, "dt50": {"system": 6.0, "soil": 39.307370635513244, "surfaceWater": 6.0, "sediment": 6.0}, "plant_uptake": 0.5, "name": "Compound -8582958084685536757", "model_specific_data": {}, "metabolites": []}}]}}