{"gap": {"type": "relative", "arguments": {"name": "GAP -296091488377847865", "modelCrop": "WC", "rate": 250.0, "apply_every_n_years": 1, "number_of_applications": 2, "interval": 14, "model_specific_data": {}, "bbch": 31, "season": 0}}, "compound": {"molarMass": 300.0, "water_solubility": 0.0010175857819320511, "vapor_pressure": 9.39035126515109e-09, "reference_temperature": 20.0, "koc": 81.96685355288679, "freundlich": 1.190975759693297, "dt50": {"system": 6.0, "soil": 179.97511314240518, "surfaceWater": 6.0, "sediment": 6.0}, "plant_uptake": 0.0, "name": "Compound 2308262156433345737", "model_specific_data": {}, "metabolites": [{"formation_fraction": 0.2, "metabolite": {"molarMass": 300.0, "water_solubility": 0.005721411597684059, "vapor_pressure": 4.305712199276491e-06, "reference_temperature": 20.0, "koc": 401.7995312491241, "freundlich": 1.1562105243863354, "dt50": {"system": 6.0, "soil": 74.02535010582211, "surfaceWater": 6.0, "sediment": 6.0}, "plant_uptake": 0.5, "name": "Compound -2996350380801216370", "model_specific_data": {}, "metabolites": []}}]}}