{"gap": {"type": "relative", "arguments": {"name": "GAP -296091488377847865", "modelCrop": "WC", "rate": 250.0, "apply_every_n_years": 1, "number_of_applications": 2, "interval": 14, "model_specific_data": {}, "bbch": 31, "season": 0}}, "compound": {"molarMass": 300.0, "water_solubility": 0.00510848830376181, "vapor_pressure": 0.00047472993047732, "reference_temperature": 20.0, "koc": 3209.656880860666, "freundlich": 0.8356233493959117, "dt50": {"system": 6.0, "soil": 84.00937550815006, "surfaceWater": 6.0, "sediment": 6.0}, "plant_uptake": 0.0, "name": "Compound 4657001620092800267", "model_specific_data": {}, "metabolites": [{"formation_fraction": 0.2, "metabolite": {"molarMass": 300.0, "water_solubility": 0.06848534616151221, "vapor_pressure": 0.00519245233835498, "reference_temperature": 20.0, "koc": 4815.848158091267, "freundlich": 1.0740950163166512, "dt50": {"system": 6.0, "soil": 176.53634504572935, "surfaceWater": 6.0, "sediment": 6.0}, "plant_uptake": 0.5, "name": "Compound 6071756817218931117", "model_specific_data": {}, "metabolites": []}}]}}